{"data":[{"traceID":"54083e5ac0b827f6","spans":[{"traceID":"54083e5ac0b827f6","spanID":"7f937698fff47339","flags":1,"operationName":"books","references":[{"refType":"CHILD_OF","traceID":"54083e5ac0b827f6","spanID":"a797408688497bd5"}],"startTime":1534172120782000,"duration":18000,"tags":[{"key":"span.kind","type":"string","value":"request"},{"key":"service.method","type":"string","value":"find"},{"key":"http.status_code","type":"float64","value":200},{"key":"http.method","type":"string","value":"GET"},{"key":"peer.hostname","type":"string","value":"lbBooks"},{"key":"peer.address","type":"string","value":"192.168.112.9"},{"key":"request.headers","type":"string","value":"{\"accept\":\"text/plain, text/plain, application/json, application/json, application/*+json, application/*+json, */*, */*\",\"uber-trace-id\":\"54083e5ac0b827f6%3Aa797408688497bd5%3A54083e5ac0b827f6%3A1\",\"host\":\"lbBooks:80\",\"user-agent\":\"Apache-HttpClient/4.5.5 (Java/1.8.0_111)\",\"accept-encoding\":\"gzip,deflate\",\"x-forwarded-proto\":\"http\",\"x-forwarded-for\":\"192.168.112.9\"}"},{"key":"response.headers","type":"string","value":"{\"x-dns-prefetch-control\":\"off\",\"x-frame-options\":\"SAMEORIGIN\",\"strict-transport-security\":\"max-age=15552000; includeSubDomains\",\"x-download-options\":\"noopen\",\"x-content-type-options\":\"nosniff\",\"x-xss-protection\":\"1; mode=block\",\"access-control-allow-origin\":\"*\",\"x-trace-id\":\"54083e5ac0b827f6:7f937698fff47339:a797408688497bd5:1\",\"allow\":\"GET,POST,PUT,PATCH,DELETE\",\"vary\":\"Accept, Accept-Encoding\",\"content-type\":\"application/json; charset=utf-8\",\"content-length\":\"310\",\"etag\":\"W/\\\"136-70DPyXYeb7xX8buh8QHiNSjqetA\\\"\"}"}],"logs":[{"timestamp":1534172120783000,"fields":[{"key":"event","type":"string","value":"request_received"}]},{"timestamp":1534172120800000,"fields":[{"key":"event","type":"string","value":"request_finished"}]}],"processID":"p1","warnings":null},{"traceID":"54083e5ac0b827f6","spanID":"54083e5ac0b827f6","flags":1,"operationName":"getCatalog","references":[],"startTime":1534172119635000,"duration":1174468,"tags":[{"key":"http.status_code","type":"int64","value":200},{"key":"component","type":"string","value":"java-web-servlet"},{"key":"span.kind","type":"string","value":"server"},{"key":"sampler.type","type":"string","value":"const"},{"key":"sampler.param","type":"bool","value":true},{"key":"http.url","type":"string","value":"http://localhost/catalog"},{"key":"pattern.circuitBreaker","type":"bool","value":true},{"key":"pattern.circuitBreaker.fallback","type":"bool","value":false},{"key":"http.method","type":"string","value":"GET"}],"logs":[{"timestamp":1534172119635000,"fields":[{"key":"event","type":"string","value":"preHandle"},{"key":"handler","type":"string","value":"public org.springframework.http.ResponseEntity\u003cjava.lang.String\u003e com.daimler.innolibrary_frontend.controller.BookController.getCatalog()"},{"key":"handler.class_simple_name","type":"string","value":"BookController"},{"key":"handler.method_name","type":"string","value":"getCatalog"}]},{"timestamp":1534172120809000,"fields":[{"key":"event","type":"string","value":"afterCompletion"},{"key":"handler","type":"string","value":"public org.springframework.http.ResponseEntity\u003cjava.lang.String\u003e com.daimler.innolibrary_frontend.controller.BookController.getCatalog()"}]}],"processID":"p2","warnings":null},{"traceID":"54083e5ac0b827f6","spanID":"a797408688497bd5","flags":1,"operationName":"GET","references":[{"refType":"CHILD_OF","traceID":"54083e5ac0b827f6","spanID":"54083e5ac0b827f6"}],"startTime":1534172120779000,"duration":22063,"tags":[{"key":"http.status_code","type":"int64","value":200},{"key":"component","type":"string","value":"java-spring-rest-template"},{"key":"span.kind","type":"string","value":"client"},{"key":"http.url","type":"string","value":"http://lbBooks:80/books"},{"key":"peer.port","type":"int64","value":80},{"key":"http.method","type":"string","value":"GET"}],"logs":[],"processID":"p2","warnings":null},{"traceID":"54083e5ac0b827f6","spanID":"f9bfb2a2553ae346","flags":1,"operationName":"POST","references":[{"refType":"CHILD_OF","traceID":"54083e5ac0b827f6","spanID":"54083e5ac0b827f6"}],"startTime":1534172119640000,"duration":1133143,"tags":[{"key":"http.status_code","type":"int64","value":201},{"key":"component","type":"string","value":"java-spring-rest-template"},{"key":"span.kind","type":"string","value":"client"},{"key":"http.url","type":"string","value":"http://lbUsers:80/authentication"},{"key":"peer.port","type":"int64","value":80},{"key":"http.method","type":"string","value":"POST"}],"logs":[],"processID":"p2","warnings":null},{"traceID":"54083e5ac0b827f6","spanID":"96ae4e11528908c5","flags":1,"operationName":"authentication","references":[{"refType":"CHILD_OF","traceID":"54083e5ac0b827f6","spanID":"f9bfb2a2553ae346"}],"startTime":1534172119651571,"duration":1110000,"tags":[{"key":"span.kind","type":"string","value":"request"},{"key":"service.method","type":"string","value":"create"},{"key":"data","type":"string","value":"{\"email\":\"admin@admin.de\",\"password\":\"testpassword\",\"strategy\":\"local\"}"},{"key":"service.method","type":"string","value":"find"},{"key":"query","type":"string","value":"{\"email\":\"admin@admin.de\",\"$limit\":1}"},{"key":"http.status_code","type":"float64","value":201},{"key":"http.method","type":"string","value":"POST"},{"key":"peer.hostname","type":"string","value":"lbUsers"},{"key":"peer.address","type":"string","value":"192.168.112.9"},{"key":"request.headers","type":"string","value":"{\"accept\":\"text/plain, text/plain, application/json, application/json, application/*+json, application/*+json, */*, */*\",\"content-type\":\"application/json\",\"uber-trace-id\":\"54083e5ac0b827f6%3Af9bfb2a2553ae346%3A54083e5ac0b827f6%3A1\",\"content-length\":\"80\",\"host\":\"lbUsers:80\",\"user-agent\":\"Apache-HttpClient/4.5.5 (Java/1.8.0_111)\",\"accept-encoding\":\"gzip,deflate\",\"x-forwarded-proto\":\"http\",\"x-forwarded-for\":\"192.168.112.9\"}"},{"key":"response.headers","type":"string","value":"{\"x-dns-prefetch-control\":\"off\",\"x-frame-options\":\"SAMEORIGIN\",\"strict-transport-security\":\"max-age=15552000; includeSubDomains\",\"x-download-options\":\"noopen\",\"x-content-type-options\":\"nosniff\",\"x-xss-protection\":\"1; mode=block\",\"access-control-allow-origin\":\"*\",\"x-trace-id\":\"54083e5ac0b827f6:96ae4e11528908c5:f9bfb2a2553ae346:1\",\"allow\":\"POST,DELETE\",\"vary\":\"Accept, Accept-Encoding\",\"content-type\":\"application/json; charset=utf-8\",\"content-length\":\"335\",\"etag\":\"W/\\\"14f-+6bB3uZl62AeNj4zBiyjp0cR9yw\\\"\"}"}],"logs":[{"timestamp":1534172119652571,"fields":[{"key":"event","type":"string","value":"request_received"}]},{"timestamp":1534172120760571,"fields":[{"key":"event","type":"string","value":"request_finished"}]}],"processID":"p3","warnings":null}],"processes":{"p1":{"serviceName":"books","tags":[{"key":"client-uuid","type":"string","value":"9e464d71-6365-4802-be1f-58465732f682"},{"key":"ip","type":"float64","value":-1062703102},{"key":"jaeger.hostname","type":"string","value":"47bae12ebd8d"},{"key":"jaeger.version","type":"string","value":"Node-3.11.0"}]},"p2":{"serviceName":"frontend","tags":[{"key":"hostname","type":"string","value":"aae2095b2777"},{"key":"ip","type":"string","value":"192.168.112.9"},{"key":"jaeger.version","type":"string","value":"Java-0.27.0"}]},"p3":{"serviceName":"users","tags":[{"key":"client-uuid","type":"string","value":"2f4728f9-d81e-4c4d-a8d6-85a06f920a90"},{"key":"ip","type":"float64","value":-1062703101},{"key":"jaeger.hostname","type":"string","value":"e41b23dc21a9"},{"key":"jaeger.version","type":"string","value":"Node-3.11.0"}]}},"warnings":null},{"traceID":"dc725d6bd5d32ef1","spans":[{"traceID":"dc725d6bd5d32ef1","spanID":"48e10b7fb076b4be","flags":1,"operationName":"authentication","references":[{"refType":"CHILD_OF","traceID":"dc725d6bd5d32ef1","spanID":"ab0a1685d545f73e"}],"startTime":1534172121889000,"duration":1074000,"tags":[{"key":"span.kind","type":"string","value":"request"},{"key":"service.method","type":"string","value":"create"},{"key":"data","type":"string","value":"{\"email\":\"admin@admin.de\",\"password\":\"testpassword\",\"strategy\":\"local\"}"},{"key":"service.method","type":"string","value":"find"},{"key":"query","type":"string","value":"{\"email\":\"admin@admin.de\",\"$limit\":1}"},{"key":"http.status_code","type":"float64","value":201},{"key":"http.method","type":"string","value":"POST"},{"key":"peer.hostname","type":"string","value":"lbUsers"},{"key":"peer.address","type":"string","value":"192.168.112.10"},{"key":"request.headers","type":"string","value":"{\"accept\":\"text/plain, text/plain, application/json, application/json, application/*+json, application/*+json, */*, */*\",\"content-type\":\"application/json\",\"uber-trace-id\":\"dc725d6bd5d32ef1%3Aab0a1685d545f73e%3Adc725d6bd5d32ef1%3A1\",\"content-length\":\"80\",\"host\":\"lbUsers:80\",\"user-agent\":\"Apache-HttpClient/4.5.5 (Java/1.8.0_111)\",\"accept-encoding\":\"gzip,deflate\",\"x-forwarded-proto\":\"http\",\"x-forwarded-for\":\"192.168.112.10\"}"},{"key":"response.headers","type":"string","value":"{\"x-dns-prefetch-control\":\"off\",\"x-frame-options\":\"SAMEORIGIN\",\"strict-transport-security\":\"max-age=15552000; includeSubDomains\",\"x-download-options\":\"noopen\",\"x-content-type-options\":\"nosniff\",\"x-xss-protection\":\"1; mode=block\",\"access-control-allow-origin\":\"*\",\"x-trace-id\":\"dc725d6bd5d32ef1:48e10b7fb076b4be:ab0a1685d545f73e:1\",\"allow\":\"POST,DELETE\",\"vary\":\"Accept, Accept-Encoding\",\"content-type\":\"application/json; charset=utf-8\",\"content-length\":\"335\",\"etag\":\"W/\\\"14f-IdDZAkUdASY9ptj2UzIL5gz9x7M\\\"\"}"}],"logs":[{"timestamp":1534172121889000,"fields":[{"key":"event","type":"string","value":"request_received"}]},{"timestamp":1534172122963000,"fields":[{"key":"event","type":"string","value":"request_finished"}]}],"processID":"p1","warnings":null},{"traceID":"dc725d6bd5d32ef1","spanID":"ab0a1685d545f73e","flags":1,"operationName":"POST","references":[{"refType":"CHILD_OF","traceID":"dc725d6bd5d32ef1","spanID":"dc725d6bd5d32ef1"}],"startTime":1534172121885000,"duration":1078415,"tags":[{"key":"http.status_code","type":"int64","value":201},{"key":"component","type":"string","value":"java-spring-rest-template"},{"key":"span.kind","type":"string","value":"client"},{"key":"http.url","type":"string","value":"http://lbUsers:80/authentication"},{"key":"peer.port","type":"int64","value":80},{"key":"http.method","type":"string","value":"POST"}],"logs":[],"processID":"p2","warnings":null},{"traceID":"dc725d6bd5d32ef1","spanID":"e64c38bcb3995f6b","flags":1,"operationName":"GET","references":[{"refType":"CHILD_OF","traceID":"dc725d6bd5d32ef1","spanID":"dc725d6bd5d32ef1"}],"startTime":1534172122966000,"duration":34115,"tags":[{"key":"http.status_code","type":"int64","value":200},{"key":"component","type":"string","value":"java-spring-rest-template"},{"key":"span.kind","type":"string","value":"client"},{"key":"http.url","type":"string","value":"http://lbBooks:80/books"},{"key":"peer.port","type":"int64","value":80},{"key":"http.method","type":"string","value":"GET"}],"logs":[],"processID":"p2","warnings":null},{"traceID":"dc725d6bd5d32ef1","spanID":"dc725d6bd5d32ef1","flags":1,"operationName":"getCatalog","references":[],"startTime":1534172121882000,"duration":1129576,"tags":[{"key":"http.status_code","type":"int64","value":200},{"key":"component","type":"string","value":"java-web-servlet"},{"key":"span.kind","type":"string","value":"server"},{"key":"sampler.type","type":"string","value":"const"},{"key":"sampler.param","type":"bool","value":true},{"key":"http.url","type":"string","value":"http://localhost/catalog"},{"key":"pattern.circuitBreaker","type":"bool","value":true},{"key":"pattern.circuitBreaker.fallback","type":"bool","value":false},{"key":"http.method","type":"string","value":"GET"}],"logs":[{"timestamp":1534172121883000,"fields":[{"key":"event","type":"string","value":"preHandle"},{"key":"handler","type":"string","value":"public org.springframework.http.ResponseEntity\u003cjava.lang.String\u003e com.daimler.innolibrary_frontend.controller.BookController.getCatalog()"},{"key":"handler.class_simple_name","type":"string","value":"BookController"},{"key":"handler.method_name","type":"string","value":"getCatalog"}]},{"timestamp":1534172123010000,"fields":[{"key":"event","type":"string","value":"afterCompletion"},{"key":"handler","type":"string","value":"public org.springframework.http.ResponseEntity\u003cjava.lang.String\u003e com.daimler.innolibrary_frontend.controller.BookController.getCatalog()"}]}],"processID":"p2","warnings":null},{"traceID":"dc725d6bd5d32ef1","spanID":"9bd156214879a4b8","flags":1,"operationName":"books","references":[{"refType":"CHILD_OF","traceID":"dc725d6bd5d32ef1","spanID":"e64c38bcb3995f6b"}],"startTime":1534172122971000,"duration":28000,"tags":[{"key":"span.kind","type":"string","value":"request"},{"key":"service.method","type":"string","value":"find"},{"key":"http.status_code","type":"float64","value":200},{"key":"http.method","type":"string","value":"GET"},{"key":"peer.hostname","type":"string","value":"lbBooks"},{"key":"peer.address","type":"string","value":"192.168.112.10"},{"key":"request.headers","type":"string","value":"{\"accept\":\"text/plain, text/plain, application/json, application/json, application/*+json, application/*+json, */*, */*\",\"uber-trace-id\":\"dc725d6bd5d32ef1%3Ae64c38bcb3995f6b%3Adc725d6bd5d32ef1%3A1\",\"host\":\"lbBooks:80\",\"user-agent\":\"Apache-HttpClient/4.5.5 (Java/1.8.0_111)\",\"accept-encoding\":\"gzip,deflate\",\"x-forwarded-proto\":\"http\",\"x-forwarded-for\":\"192.168.112.10\"}"},{"key":"response.headers","type":"string","value":"{\"x-dns-prefetch-control\":\"off\",\"x-frame-options\":\"SAMEORIGIN\",\"strict-transport-security\":\"max-age=15552000; includeSubDomains\",\"x-download-options\":\"noopen\",\"x-content-type-options\":\"nosniff\",\"x-xss-protection\":\"1; mode=block\",\"access-control-allow-origin\":\"*\",\"x-trace-id\":\"dc725d6bd5d32ef1:9bd156214879a4b8:e64c38bcb3995f6b:1\",\"allow\":\"GET,POST,PUT,PATCH,DELETE\",\"vary\":\"Accept, Accept-Encoding\",\"content-type\":\"application/json; charset=utf-8\",\"content-length\":\"310\",\"etag\":\"W/\\\"136-70DPyXYeb7xX8buh8QHiNSjqetA\\\"\"}"}],"logs":[{"timestamp":1534172122971000,"fields":[{"key":"event","type":"string","value":"request_received"}]},{"timestamp":1534172122999000,"fields":[{"key":"event","type":"string","value":"request_finished"}]}],"processID":"p3","warnings":null}],"processes":{"p1":{"serviceName":"users","tags":[{"key":"client-uuid","type":"string","value":"05377051-6184-4b76-9b5b-2df32530b005"},{"key":"ip","type":"float64","value":-1062703099},{"key":"jaeger.hostname","type":"string","value":"a0afa8809983"},{"key":"jaeger.version","type":"string","value":"Node-3.11.0"}]},"p2":{"serviceName":"frontend","tags":[{"key":"hostname","type":"string","value":"685cd33f7b53"},{"key":"ip","type":"string","value":"192.168.112.10"},{"key":"jaeger.version","type":"string","value":"Java-0.27.0"}]},"p3":{"serviceName":"books","tags":[{"key":"client-uuid","type":"string","value":"9e464d71-6365-4802-be1f-58465732f682"},{"key":"ip","type":"float64","value":-1062703102},{"key":"jaeger.hostname","type":"string","value":"47bae12ebd8d"},{"key":"jaeger.version","type":"string","value":"Node-3.11.0"}]}},"warnings":null},{"traceID":"4e8b823b4aa44125","spans":[{"traceID":"4e8b823b4aa44125","spanID":"45367aa099f92440","flags":1,"operationName":"authentication","references":[{"refType":"CHILD_OF","traceID":"4e8b823b4aa44125","spanID":"99b9a1bfe8874904"}],"startTime":1534171906330000,"duration":1090000,"tags":[{"key":"span.kind","type":"string","value":"request"},{"key":"service.method","type":"string","value":"create"},{"key":"data","type":"string","value":"{\"email\":\"admin@admin.de\",\"password\":\"testpassword\",\"strategy\":\"local\"}"},{"key":"service.method","type":"string","value":"find"},{"key":"query","type":"string","value":"{\"email\":\"admin@admin.de\",\"$limit\":1}"},{"key":"http.status_code","type":"float64","value":201},{"key":"http.method","type":"string","value":"POST"},{"key":"peer.hostname","type":"string","value":"lbUsers"},{"key":"peer.address","type":"string","value":"192.168.112.10"},{"key":"request.headers","type":"string","value":"{\"accept\":\"text/plain, text/plain, application/json, application/json, application/*+json, application/*+json, */*, */*\",\"content-type\":\"application/json\",\"uber-trace-id\":\"4e8b823b4aa44125%3A99b9a1bfe8874904%3A4e8b823b4aa44125%3A1\",\"content-length\":\"80\",\"host\":\"lbUsers:80\",\"user-agent\":\"Apache-HttpClient/4.5.5 (Java/1.8.0_111)\",\"accept-encoding\":\"gzip,deflate\",\"x-forwarded-proto\":\"http\",\"x-forwarded-for\":\"192.168.112.10\"}"},{"key":"response.headers","type":"string","value":"{\"x-dns-prefetch-control\":\"off\",\"x-frame-options\":\"SAMEORIGIN\",\"strict-transport-security\":\"max-age=15552000; includeSubDomains\",\"x-download-options\":\"noopen\",\"x-content-type-options\":\"nosniff\",\"x-xss-protection\":\"1; mode=block\",\"access-control-allow-origin\":\"*\",\"x-trace-id\":\"4e8b823b4aa44125:45367aa099f92440:99b9a1bfe8874904:1\",\"allow\":\"POST,DELETE\",\"vary\":\"Accept, Accept-Encoding\",\"content-type\":\"application/json; charset=utf-8\",\"content-length\":\"335\",\"etag\":\"W/\\\"14f-2fJP3npEUr1rh0v6/q+0jo2rxTM\\\"\"}"}],"logs":[{"timestamp":1534171906332000,"fields":[{"key":"event","type":"string","value":"request_received"}]},{"timestamp":1534171907418000,"fields":[{"key":"event","type":"string","value":"request_finished"}]}],"processID":"p1","warnings":null},{"traceID":"4e8b823b4aa44125","spanID":"4e8b823b4aa44125","flags":1,"operationName":"getCatalog","references":[],"startTime":1534171902286000,"duration":5110938,"tags":[{"key":"http.status_code","type":"int64","value":200},{"key":"component","type":"string","value":"java-web-servlet"},{"key":"span.kind","type":"string","value":"server"},{"key":"sampler.type","type":"string","value":"const"},{"key":"sampler.param","type":"bool","value":true},{"key":"http.url","type":"string","value":"http://localhost/catalog"},{"key":"pattern.circuitBreaker","type":"bool","value":true},{"key":"pattern.circuitBreaker.fallback","type":"bool","value":true},{"key":"http.method","type":"string","value":"GET"}],"logs":[{"timestamp":1534171902287000,"fields":[{"key":"event","type":"string","value":"preHandle"},{"key":"handler","type":"string","value":"public org.springframework.http.ResponseEntity\u003cjava.lang.String\u003e com.daimler.innolibrary_frontend.controller.BookController.getCatalog()"},{"key":"handler.class_simple_name","type":"string","value":"BookController"},{"key":"handler.method_name","type":"string","value":"getCatalog"}]},{"timestamp":1534171907397000,"fields":[{"key":"event","type":"string","value":"afterCompletion"},{"key":"handler","type":"string","value":"public org.springframework.http.ResponseEntity\u003cjava.lang.String\u003e com.daimler.innolibrary_frontend.controller.BookController.getCatalog()"}]}],"processID":"p2","warnings":null},{"traceID":"4e8b823b4aa44125","spanID":"99b9a1bfe8874904","flags":1,"operationName":"POST","references":[{"refType":"CHILD_OF","traceID":"4e8b823b4aa44125","spanID":"4e8b823b4aa44125"}],"startTime":1534171905798000,"duration":1635023,"tags":[{"key":"http.status_code","type":"int64","value":201},{"key":"component","type":"string","value":"java-spring-rest-template"},{"key":"span.kind","type":"string","value":"client"},{"key":"http.url","type":"string","value":"http://lbUsers:80/authentication"},{"key":"peer.port","type":"int64","value":80},{"key":"http.method","type":"string","value":"POST"}],"logs":[],"processID":"p2","warnings":null},{"traceID":"4e8b823b4aa44125","spanID":"344366b1a022c0cd","flags":1,"operationName":"GET","references":[{"refType":"CHILD_OF","traceID":"4e8b823b4aa44125","spanID":"4e8b823b4aa44125"}],"startTime":1534171907437000,"duration":49526,"tags":[{"key":"http.status_code","type":"int64","value":200},{"key":"component","type":"string","value":"java-spring-rest-template"},{"key":"span.kind","type":"string","value":"client"},{"key":"http.url","type":"string","value":"http://lbBooks:80/books"},{"key":"peer.port","type":"int64","value":80},{"key":"http.method","type":"string","value":"GET"}],"logs":[],"processID":"p2","warnings":null},{"traceID":"4e8b823b4aa44125","spanID":"b8c0305a04073124","flags":1,"operationName":"books","references":[{"refType":"CHILD_OF","traceID":"4e8b823b4aa44125","spanID":"344366b1a022c0cd"}],"startTime":1534171907484000,"duration":2000,"tags":[{"key":"span.kind","type":"string","value":"request"},{"key":"service.method","type":"string","value":"find"},{"key":"http.status_code","type":"float64","value":200},{"key":"http.method","type":"string","value":"GET"},{"key":"peer.hostname","type":"string","value":"lbBooks"},{"key":"peer.address","type":"string","value":"192.168.112.10"},{"key":"request.headers","type":"string","value":"{\"accept\":\"text/plain, text/plain, application/json, application/json, application/*+json, application/*+json, */*, */*\",\"uber-trace-id\":\"4e8b823b4aa44125%3A344366b1a022c0cd%3A4e8b823b4aa44125%3A1\",\"host\":\"lbBooks:80\",\"user-agent\":\"Apache-HttpClient/4.5.5 (Java/1.8.0_111)\",\"accept-encoding\":\"gzip,deflate\",\"x-forwarded-proto\":\"http\",\"x-forwarded-for\":\"192.168.112.10\"}"},{"key":"response.headers","type":"string","value":"{\"x-dns-prefetch-control\":\"off\",\"x-frame-options\":\"SAMEORIGIN\",\"strict-transport-security\":\"max-age=15552000; includeSubDomains\",\"x-download-options\":\"noopen\",\"x-content-type-options\":\"nosniff\",\"x-xss-protection\":\"1; mode=block\",\"access-control-allow-origin\":\"*\",\"x-trace-id\":\"4e8b823b4aa44125:b8c0305a04073124:344366b1a022c0cd:1\",\"allow\":\"GET,POST,PUT,PATCH,DELETE\",\"vary\":\"Accept, Accept-Encoding\",\"content-type\":\"application/json; charset=utf-8\",\"content-length\":\"310\",\"etag\":\"W/\\\"136-70DPyXYeb7xX8buh8QHiNSjqetA\\\"\"}"}],"logs":[{"timestamp":1534171907484000,"fields":[{"key":"event","type":"string","value":"request_received"}]},{"timestamp":1534171907486000,"fields":[{"key":"event","type":"string","value":"request_finished"}]}],"processID":"p3","warnings":null}],"processes":{"p1":{"serviceName":"users","tags":[{"key":"client-uuid","type":"string","value":"f652a29a-d1a4-41ba-9c08-cfef1ca91212"},{"key":"ip","type":"float64","value":-1062703098},{"key":"jaeger.hostname","type":"string","value":"df140c843700"},{"key":"jaeger.version","type":"string","value":"Node-3.11.0"}]},"p2":{"serviceName":"frontend","tags":[{"key":"hostname","type":"string","value":"685cd33f7b53"},{"key":"ip","type":"string","value":"192.168.112.10"},{"key":"jaeger.version","type":"string","value":"Java-0.27.0"}]},"p3":{"serviceName":"books","tags":[{"key":"client-uuid","type":"string","value":"9e464d71-6365-4802-be1f-58465732f682"},{"key":"ip","type":"float64","value":-1062703102},{"key":"jaeger.hostname","type":"string","value":"47bae12ebd8d"},{"key":"jaeger.version","type":"string","value":"Node-3.11.0"}]}},"warnings":null},{"traceID":"71ed84cd34e72d6d","spans":[{"traceID":"71ed84cd34e72d6d","spanID":"ed5c6eca857d1cd6","flags":1,"operationName":"POST","references":[{"refType":"CHILD_OF","traceID":"71ed84cd34e72d6d","spanID":"71ed84cd34e72d6d"}],"startTime":1534172172173000,"duration":953337,"tags":[{"key":"http.status_code","type":"int64","value":201},{"key":"component","type":"string","value":"java-spring-rest-template"},{"key":"span.kind","type":"string","value":"client"},{"key":"http.url","type":"string","value":"http://lbUsers:80/authentication"},{"key":"peer.port","type":"int64","value":80},{"key":"http.method","type":"string","value":"POST"}],"logs":[],"processID":"p1","warnings":null},{"traceID":"71ed84cd34e72d6d","spanID":"47233d28722b9e36","flags":1,"operationName":"POST","references":[{"refType":"CHILD_OF","traceID":"71ed84cd34e72d6d","spanID":"71ed84cd34e72d6d"}],"startTime":1534172173129000,"duration":37382,"tags":[{"key":"http.status_code","type":"int64","value":201},{"key":"component","type":"string","value":"java-spring-rest-template"},{"key":"span.kind","type":"string","value":"client"},{"key":"http.url","type":"string","value":"http://lbBooks:80/books"},{"key":"peer.port","type":"int64","value":80},{"key":"http.method","type":"string","value":"POST"}],"logs":[],"processID":"p1","warnings":null},{"traceID":"71ed84cd34e72d6d","spanID":"71ed84cd34e72d6d","flags":1,"operationName":"createBook","references":[],"startTime":1534172172163000,"duration":1009732,"tags":[{"key":"http.status_code","type":"int64","value":201},{"key":"component","type":"string","value":"java-web-servlet"},{"key":"span.kind","type":"string","value":"server"},{"key":"sampler.type","type":"string","value":"const"},{"key":"sampler.param","type":"bool","value":true},{"key":"http.url","type":"string","value":"http://localhost/createBook"},{"key":"pattern.circuitBreaker","type":"bool","value":true},{"key":"pattern.circuitBreaker.fallback","type":"bool","value":false},{"key":"http.method","type":"string","value":"GET"}],"logs":[{"timestamp":1534172172164000,"fields":[{"key":"event","type":"string","value":"preHandle"},{"key":"handler","type":"string","value":"public org.springframework.http.ResponseEntity\u003cjava.lang.String\u003e com.daimler.innolibrary_frontend.controller.BookController.createBook()"},{"key":"handler.class_simple_name","type":"string","value":"BookController"},{"key":"handler.method_name","type":"string","value":"createBook"}]},{"timestamp":1534172173173000,"fields":[{"key":"event","type":"string","value":"afterCompletion"},{"key":"handler","type":"string","value":"public org.springframework.http.ResponseEntity\u003cjava.lang.String\u003e com.daimler.innolibrary_frontend.controller.BookController.createBook()"}]}],"processID":"p1","warnings":null},{"traceID":"71ed84cd34e72d6d","spanID":"fe5844dcb5c82873","flags":1,"operationName":"authentication","references":[{"refType":"CHILD_OF","traceID":"71ed84cd34e72d6d","spanID":"ed5c6eca857d1cd6"}],"startTime":1534172172179000,"duration":946000,"tags":[{"key":"span.kind","type":"string","value":"request"},{"key":"service.method","type":"string","value":"create"},{"key":"data","type":"string","value":"{\"email\":\"admin@admin.de\",\"password\":\"testpassword\",\"strategy\":\"local\"}"},{"key":"service.method","type":"string","value":"find"},{"key":"query","type":"string","value":"{\"email\":\"admin@admin.de\",\"$limit\":1}"},{"key":"http.status_code","type":"float64","value":201},{"key":"http.method","type":"string","value":"POST"},{"key":"peer.hostname","type":"string","value":"lbUsers"},{"key":"peer.address","type":"string","value":"192.168.112.10"},{"key":"request.headers","type":"string","value":"{\"accept\":\"text/plain, text/plain, application/json, application/json, application/*+json, application/*+json, */*, */*\",\"content-type\":\"application/json\",\"uber-trace-id\":\"71ed84cd34e72d6d%3Aed5c6eca857d1cd6%3A71ed84cd34e72d6d%3A1\",\"content-length\":\"80\",\"host\":\"lbUsers:80\",\"user-agent\":\"Apache-HttpClient/4.5.5 (Java/1.8.0_111)\",\"accept-encoding\":\"gzip,deflate\",\"x-forwarded-proto\":\"http\",\"x-forwarded-for\":\"192.168.112.10\"}"},{"key":"response.headers","type":"string","value":"{\"x-dns-prefetch-control\":\"off\",\"x-frame-options\":\"SAMEORIGIN\",\"strict-transport-security\":\"max-age=15552000; includeSubDomains\",\"x-download-options\":\"noopen\",\"x-content-type-options\":\"nosniff\",\"x-xss-protection\":\"1; mode=block\",\"access-control-allow-origin\":\"*\",\"x-trace-id\":\"71ed84cd34e72d6d:fe5844dcb5c82873:ed5c6eca857d1cd6:1\",\"allow\":\"POST,DELETE\",\"vary\":\"Accept, Accept-Encoding\",\"content-type\":\"application/json; charset=utf-8\",\"content-length\":\"335\",\"etag\":\"W/\\\"14f-cmVR2p2a5oJZ0NDYM6CIXMS3ik8\\\"\"}"}],"logs":[{"timestamp":1534172172179000,"fields":[{"key":"event","type":"string","value":"request_received"}]},{"timestamp":1534172173125000,"fields":[{"key":"event","type":"string","value":"request_finished"}]}],"processID":"p2","warnings":null},{"traceID":"71ed84cd34e72d6d","spanID":"4ac83a938ccbd4f1","flags":1,"operationName":"books","references":[{"refType":"CHILD_OF","traceID":"71ed84cd34e72d6d","spanID":"47233d28722b9e36"}],"startTime":1534172173144000,"duration":22000,"tags":[{"key":"span.kind","type":"string","value":"request"},{"key":"service.method","type":"string","value":"create"},{"key":"data","type":"string","value":"{\"isbn\":\"93628723361\",\"title\":\"title0\",\"author\":\"author0\",\"createdAt\":\"2018-08-13T14:56:13.145Z\",\"updatedAt\":\"2018-08-13T14:56:13.145Z\"}"},{"key":"http.status_code","type":"float64","value":201},{"key":"http.method","type":"string","value":"POST"},{"key":"peer.hostname","type":"string","value":"lbBooks"},{"key":"peer.address","type":"string","value":"192.168.112.10"},{"key":"request.headers","type":"string","value":"{\"accept\":\"text/plain, text/plain, application/json, application/json, application/*+json, application/*+json, */*, */*\",\"content-type\":\"application/json\",\"uber-trace-id\":\"71ed84cd34e72d6d%3A47233d28722b9e36%3A71ed84cd34e72d6d%3A1\",\"content-length\":\"63\",\"host\":\"lbBooks:80\",\"user-agent\":\"Apache-HttpClient/4.5.5 (Java/1.8.0_111)\",\"accept-encoding\":\"gzip,deflate\",\"x-forwarded-proto\":\"http\",\"x-forwarded-for\":\"192.168.112.10\"}"},{"key":"response.headers","type":"string","value":"{\"x-dns-prefetch-control\":\"off\",\"x-frame-options\":\"SAMEORIGIN\",\"strict-transport-security\":\"max-age=15552000; includeSubDomains\",\"x-download-options\":\"noopen\",\"x-content-type-options\":\"nosniff\",\"x-xss-protection\":\"1; mode=block\",\"access-control-allow-origin\":\"*\",\"x-trace-id\":\"71ed84cd34e72d6d:4ac83a938ccbd4f1:47233d28722b9e36:1\",\"allow\":\"GET,POST,PUT,PATCH,DELETE\",\"vary\":\"Accept, Accept-Encoding\",\"content-type\":\"application/json; charset=utf-8\",\"content-length\":\"161\",\"etag\":\"W/\\\"a1-FiVXWejM4YdqMUTCzHQ1JmQncPI\\\"\"}"}],"logs":[{"timestamp":1534172173144000,"fields":[{"key":"event","type":"string","value":"request_received"}]},{"timestamp":1534172173166000,"fields":[{"key":"event","type":"string","value":"request_finished"}]}],"processID":"p3","warnings":null}],"processes":{"p1":{"serviceName":"frontend","tags":[{"key":"hostname","type":"string","value":"685cd33f7b53"},{"key":"ip","type":"string","value":"192.168.112.10"},{"key":"jaeger.version","type":"string","value":"Java-0.27.0"}]},"p2":{"serviceName":"users","tags":[{"key":"client-uuid","type":"string","value":"05377051-6184-4b76-9b5b-2df32530b005"},{"key":"ip","type":"float64","value":-1062703099},{"key":"jaeger.hostname","type":"string","value":"a0afa8809983"},{"key":"jaeger.version","type":"string","value":"Node-3.11.0"}]},"p3":{"serviceName":"books","tags":[{"key":"client-uuid","type":"string","value":"9e464d71-6365-4802-be1f-58465732f682"},{"key":"ip","type":"float64","value":-1062703102},{"key":"jaeger.hostname","type":"string","value":"47bae12ebd8d"},{"key":"jaeger.version","type":"string","value":"Node-3.11.0"}]}},"warnings":null},{"traceID":"ad6ff3512b1e6b97","spans":[{"traceID":"ad6ff3512b1e6b97","spanID":"ef08d16c4a92b8cc","flags":1,"operationName":"POST","references":[{"refType":"CHILD_OF","traceID":"ad6ff3512b1e6b97","spanID":"ad6ff3512b1e6b97"}],"startTime":1534172174466000,"duration":1036837,"tags":[{"key":"http.status_code","type":"int64","value":201},{"key":"component","type":"string","value":"java-spring-rest-template"},{"key":"span.kind","type":"string","value":"client"},{"key":"http.url","type":"string","value":"http://lbUsers:80/authentication"},{"key":"peer.port","type":"int64","value":80},{"key":"http.method","type":"string","value":"POST"}],"logs":[],"processID":"p1","warnings":null},{"traceID":"ad6ff3512b1e6b97","spanID":"a05fe74470955b7c","flags":1,"operationName":"POST","references":[{"refType":"CHILD_OF","traceID":"ad6ff3512b1e6b97","spanID":"ad6ff3512b1e6b97"}],"startTime":1534172175563000,"duration":9744,"tags":[{"key":"http.status_code","type":"int64","value":201},{"key":"component","type":"string","value":"java-spring-rest-template"},{"key":"span.kind","type":"string","value":"client"},{"key":"http.url","type":"string","value":"http://lbBooks:80/books"},{"key":"peer.port","type":"int64","value":80},{"key":"http.method","type":"string","value":"POST"}],"logs":[],"processID":"p1","warnings":null},{"traceID":"ad6ff3512b1e6b97","spanID":"ad6ff3512b1e6b97","flags":1,"operationName":"createBook","references":[],"startTime":1534172174393000,"duration":1186926,"tags":[{"key":"http.status_code","type":"int64","value":201},{"key":"component","type":"string","value":"java-web-servlet"},{"key":"span.kind","type":"string","value":"server"},{"key":"sampler.type","type":"string","value":"const"},{"key":"sampler.param","type":"bool","value":true},{"key":"http.url","type":"string","value":"http://localhost/createBook"},{"key":"pattern.circuitBreaker","type":"bool","value":true},{"key":"pattern.circuitBreaker.fallback","type":"bool","value":false},{"key":"http.method","type":"string","value":"GET"}],"logs":[{"timestamp":1534172174393000,"fields":[{"key":"event","type":"string","value":"preHandle"},{"key":"handler","type":"string","value":"public org.springframework.http.ResponseEntity\u003cjava.lang.String\u003e com.daimler.innolibrary_frontend.controller.BookController.createBook()"},{"key":"handler.class_simple_name","type":"string","value":"BookController"},{"key":"handler.method_name","type":"string","value":"createBook"}]},{"timestamp":1534172175579000,"fields":[{"key":"event","type":"string","value":"afterCompletion"},{"key":"handler","type":"string","value":"public org.springframework.http.ResponseEntity\u003cjava.lang.String\u003e com.daimler.innolibrary_frontend.controller.BookController.createBook()"}]}],"processID":"p1","warnings":null},{"traceID":"ad6ff3512b1e6b97","spanID":"ee3d8f020910b135","flags":1,"operationName":"books","references":[{"refType":"CHILD_OF","traceID":"ad6ff3512b1e6b97","spanID":"a05fe74470955b7c"}],"startTime":1534172175568000,"duration":4000,"tags":[{"key":"span.kind","type":"string","value":"request"},{"key":"service.method","type":"string","value":"create"},{"key":"data","type":"string","value":"{\"isbn\":\"8143485428\",\"title\":\"title1\",\"author\":\"author1\",\"createdAt\":\"2018-08-13T14:56:15.569Z\",\"updatedAt\":\"2018-08-13T14:56:15.569Z\"}"},{"key":"http.status_code","type":"float64","value":201},{"key":"http.method","type":"string","value":"POST"},{"key":"peer.hostname","type":"string","value":"lbBooks"},{"key":"peer.address","type":"string","value":"192.168.112.10"},{"key":"request.headers","type":"string","value":"{\"accept\":\"text/plain, text/plain, application/json, application/json, application/*+json, application/*+json, */*, */*\",\"content-type\":\"application/json\",\"uber-trace-id\":\"ad6ff3512b1e6b97%3Aa05fe74470955b7c%3Aad6ff3512b1e6b97%3A1\",\"content-length\":\"62\",\"host\":\"lbBooks:80\",\"user-agent\":\"Apache-HttpClient/4.5.5 (Java/1.8.0_111)\",\"accept-encoding\":\"gzip,deflate\",\"x-forwarded-proto\":\"http\",\"x-forwarded-for\":\"192.168.112.10\"}"},{"key":"response.headers","type":"string","value":"{\"x-dns-prefetch-control\":\"off\",\"x-frame-options\":\"SAMEORIGIN\",\"strict-transport-security\":\"max-age=15552000; includeSubDomains\",\"x-download-options\":\"noopen\",\"x-content-type-options\":\"nosniff\",\"x-xss-protection\":\"1; mode=block\",\"access-control-allow-origin\":\"*\",\"x-trace-id\":\"ad6ff3512b1e6b97:ee3d8f020910b135:a05fe74470955b7c:1\",\"allow\":\"GET,POST,PUT,PATCH,DELETE\",\"vary\":\"Accept, Accept-Encoding\",\"content-type\":\"application/json; charset=utf-8\",\"content-length\":\"160\",\"etag\":\"W/\\\"a0-8QqLHMcAbEmtoyJRaWC4KzNcbsA\\\"\"}"}],"logs":[{"timestamp":1534172175568000,"fields":[{"key":"event","type":"string","value":"request_received"}]},{"timestamp":1534172175570000,"fields":[{"key":"event","type":"string","value":"request_finished"}]}],"processID":"p2","warnings":null},{"traceID":"ad6ff3512b1e6b97","spanID":"a01085bebb79efe1","flags":1,"operationName":"authentication","references":[{"refType":"CHILD_OF","traceID":"ad6ff3512b1e6b97","spanID":"ef08d16c4a92b8cc"}],"startTime":1534172174468000,"duration":1034000,"tags":[{"key":"span.kind","type":"string","value":"request"},{"key":"service.method","type":"string","value":"create"},{"key":"data","type":"string","value":"{\"email\":\"admin@admin.de\",\"password\":\"testpassword\",\"strategy\":\"local\"}"},{"key":"service.method","type":"string","value":"find"},{"key":"query","type":"string","value":"{\"email\":\"admin@admin.de\",\"$limit\":1}"},{"key":"http.status_code","type":"float64","value":201},{"key":"http.method","type":"string","value":"POST"},{"key":"peer.hostname","type":"string","value":"lbUsers"},{"key":"peer.address","type":"string","value":"192.168.112.10"},{"key":"request.headers","type":"string","value":"{\"accept\":\"text/plain, text/plain, application/json, application/json, application/*+json, application/*+json, */*, */*\",\"content-type\":\"application/json\",\"uber-trace-id\":\"ad6ff3512b1e6b97%3Aef08d16c4a92b8cc%3Aad6ff3512b1e6b97%3A1\",\"content-length\":\"80\",\"host\":\"lbUsers:80\",\"user-agent\":\"Apache-HttpClient/4.5.5 (Java/1.8.0_111)\",\"accept-encoding\":\"gzip,deflate\",\"x-forwarded-proto\":\"http\",\"x-forwarded-for\":\"192.168.112.10\"}"},{"key":"response.headers","type":"string","value":"{\"x-dns-prefetch-control\":\"off\",\"x-frame-options\":\"SAMEORIGIN\",\"strict-transport-security\":\"max-age=15552000; includeSubDomains\",\"x-download-options\":\"noopen\",\"x-content-type-options\":\"nosniff\",\"x-xss-protection\":\"1; mode=block\",\"access-control-allow-origin\":\"*\",\"x-trace-id\":\"ad6ff3512b1e6b97:a01085bebb79efe1:ef08d16c4a92b8cc:1\",\"allow\":\"POST,DELETE\",\"vary\":\"Accept, Accept-Encoding\",\"content-type\":\"application/json; charset=utf-8\",\"content-length\":\"335\",\"etag\":\"W/\\\"14f-D77YYOovNt375SMP7yFXiqeXVAs\\\"\"}"}],"logs":[{"timestamp":1534172174468000,"fields":[{"key":"event","type":"string","value":"request_received"}]},{"timestamp":1534172175502000,"fields":[{"key":"event","type":"string","value":"request_finished"}]}],"processID":"p3","warnings":null}],"processes":{"p1":{"serviceName":"frontend","tags":[{"key":"hostname","type":"string","value":"685cd33f7b53"},{"key":"ip","type":"string","value":"192.168.112.10"},{"key":"jaeger.version","type":"string","value":"Java-0.27.0"}]},"p2":{"serviceName":"books","tags":[{"key":"client-uuid","type":"string","value":"9e464d71-6365-4802-be1f-58465732f682"},{"key":"ip","type":"float64","value":-1062703102},{"key":"jaeger.hostname","type":"string","value":"47bae12ebd8d"},{"key":"jaeger.version","type":"string","value":"Node-3.11.0"}]},"p3":{"serviceName":"users","tags":[{"key":"client-uuid","type":"string","value":"2f4728f9-d81e-4c4d-a8d6-85a06f920a90"},{"key":"ip","type":"float64","value":-1062703101},{"key":"jaeger.hostname","type":"string","value":"e41b23dc21a9"},{"key":"jaeger.version","type":"string","value":"Node-3.11.0"}]}},"warnings":null},{"traceID":"cb6bac1ceaf73365","spans":[{"traceID":"cb6bac1ceaf73365","spanID":"7cf08d03fa8905b0","flags":1,"operationName":"POST","references":[{"refType":"CHILD_OF","traceID":"cb6bac1ceaf73365","spanID":"cb6bac1ceaf73365"}],"startTime":1534172180652000,"duration":5295,"tags":[{"key":"http.status_code","type":"int64","value":201},{"key":"component","type":"string","value":"java-spring-rest-template"},{"key":"span.kind","type":"string","value":"client"},{"key":"http.url","type":"string","value":"http://lbBooks:80/books"},{"key":"peer.port","type":"int64","value":80},{"key":"http.method","type":"string","value":"POST"}],"logs":[],"processID":"p1","warnings":null},{"traceID":"cb6bac1ceaf73365","spanID":"cb6bac1ceaf73365","flags":1,"operationName":"createBook","references":[],"startTime":1534172179572000,"duration":1089014,"tags":[{"key":"http.status_code","type":"int64","value":201},{"key":"component","type":"string","value":"java-web-servlet"},{"key":"span.kind","type":"string","value":"server"},{"key":"sampler.type","type":"string","value":"const"},{"key":"sampler.param","type":"bool","value":true},{"key":"http.url","type":"string","value":"http://localhost/createBook"},{"key":"pattern.circuitBreaker","type":"bool","value":true},{"key":"pattern.circuitBreaker.fallback","type":"bool","value":false},{"key":"http.method","type":"string","value":"GET"}],"logs":[{"timestamp":1534172179573000,"fields":[{"key":"event","type":"string","value":"preHandle"},{"key":"handler","type":"string","value":"public org.springframework.http.ResponseEntity\u003cjava.lang.String\u003e com.daimler.innolibrary_frontend.controller.BookController.createBook()"},{"key":"handler.class_simple_name","type":"string","value":"BookController"},{"key":"handler.method_name","type":"string","value":"createBook"}]},{"timestamp":1534172180661000,"fields":[{"key":"event","type":"string","value":"afterCompletion"},{"key":"handler","type":"string","value":"public org.springframework.http.ResponseEntity\u003cjava.lang.String\u003e com.daimler.innolibrary_frontend.controller.BookController.createBook()"}]}],"processID":"p1","warnings":null},{"traceID":"cb6bac1ceaf73365","spanID":"1ce6d682e96b77f5","flags":1,"operationName":"POST","references":[{"refType":"CHILD_OF","traceID":"cb6bac1ceaf73365","spanID":"cb6bac1ceaf73365"}],"startTime":1534172179627000,"duration":1024893,"tags":[{"key":"http.status_code","type":"int64","value":201},{"key":"component","type":"string","value":"java-spring-rest-template"},{"key":"span.kind","type":"string","value":"client"},{"key":"http.url","type":"string","value":"http://lbUsers:80/authentication"},{"key":"peer.port","type":"int64","value":80},{"key":"http.method","type":"string","value":"POST"}],"logs":[],"processID":"p1","warnings":null},{"traceID":"cb6bac1ceaf73365","spanID":"f9a563f115be5ab3","flags":1,"operationName":"books","references":[{"refType":"CHILD_OF","traceID":"cb6bac1ceaf73365","spanID":"7cf08d03fa8905b0"}],"startTime":1534172180656000,"duration":1000,"tags":[{"key":"span.kind","type":"string","value":"request"},{"key":"service.method","type":"string","value":"create"},{"key":"data","type":"string","value":"{\"isbn\":\"52780897846\",\"title\":\"title2\",\"author\":\"author2\",\"createdAt\":\"2018-08-13T14:56:20.656Z\",\"updatedAt\":\"2018-08-13T14:56:20.656Z\"}"},{"key":"http.status_code","type":"float64","value":201},{"key":"http.method","type":"string","value":"POST"},{"key":"peer.hostname","type":"string","value":"lbBooks"},{"key":"peer.address","type":"string","value":"192.168.112.10"},{"key":"request.headers","type":"string","value":"{\"accept\":\"text/plain, text/plain, application/json, application/json, application/*+json, application/*+json, */*, */*\",\"content-type\":\"application/json\",\"uber-trace-id\":\"cb6bac1ceaf73365%3A7cf08d03fa8905b0%3Acb6bac1ceaf73365%3A1\",\"content-length\":\"63\",\"host\":\"lbBooks:80\",\"user-agent\":\"Apache-HttpClient/4.5.5 (Java/1.8.0_111)\",\"accept-encoding\":\"gzip,deflate\",\"x-forwarded-proto\":\"http\",\"x-forwarded-for\":\"192.168.112.10\"}"},{"key":"response.headers","type":"string","value":"{\"x-dns-prefetch-control\":\"off\",\"x-frame-options\":\"SAMEORIGIN\",\"strict-transport-security\":\"max-age=15552000; includeSubDomains\",\"x-download-options\":\"noopen\",\"x-content-type-options\":\"nosniff\",\"x-xss-protection\":\"1; mode=block\",\"access-control-allow-origin\":\"*\",\"x-trace-id\":\"cb6bac1ceaf73365:f9a563f115be5ab3:7cf08d03fa8905b0:1\",\"allow\":\"GET,POST,PUT,PATCH,DELETE\",\"vary\":\"Accept, Accept-Encoding\",\"content-type\":\"application/json; charset=utf-8\",\"content-length\":\"161\",\"etag\":\"W/\\\"a1-BB1cdHRmR3/CcVY8TYy9Jg6y0Kw\\\"\"}"}],"logs":[{"timestamp":1534172180656000,"fields":[{"key":"event","type":"string","value":"request_received"}]},{"timestamp":1534172180657000,"fields":[{"key":"event","type":"string","value":"request_finished"}]}],"processID":"p2","warnings":null},{"traceID":"cb6bac1ceaf73365","spanID":"71cda6ef30c41022","flags":1,"operationName":"authentication","references":[{"refType":"CHILD_OF","traceID":"cb6bac1ceaf73365","spanID":"1ce6d682e96b77f5"}],"startTime":1534172179631000,"duration":1020000,"tags":[{"key":"span.kind","type":"string","value":"request"},{"key":"service.method","type":"string","value":"create"},{"key":"data","type":"string","value":"{\"email\":\"admin@admin.de\",\"password\":\"testpassword\",\"strategy\":\"local\"}"},{"key":"service.method","type":"string","value":"find"},{"key":"query","type":"string","value":"{\"email\":\"admin@admin.de\",\"$limit\":1}"},{"key":"http.status_code","type":"float64","value":201},{"key":"http.method","type":"string","value":"POST"},{"key":"peer.hostname","type":"string","value":"lbUsers"},{"key":"peer.address","type":"string","value":"192.168.112.10"},{"key":"request.headers","type":"string","value":"{\"accept\":\"text/plain, text/plain, application/json, application/json, application/*+json, application/*+json, */*, */*\",\"content-type\":\"application/json\",\"uber-trace-id\":\"cb6bac1ceaf73365%3A1ce6d682e96b77f5%3Acb6bac1ceaf73365%3A1\",\"content-length\":\"80\",\"host\":\"lbUsers:80\",\"user-agent\":\"Apache-HttpClient/4.5.5 (Java/1.8.0_111)\",\"accept-encoding\":\"gzip,deflate\",\"x-forwarded-proto\":\"http\",\"x-forwarded-for\":\"192.168.112.10\"}"},{"key":"response.headers","type":"string","value":"{\"x-dns-prefetch-control\":\"off\",\"x-frame-options\":\"SAMEORIGIN\",\"strict-transport-security\":\"max-age=15552000; includeSubDomains\",\"x-download-options\":\"noopen\",\"x-content-type-options\":\"nosniff\",\"x-xss-protection\":\"1; mode=block\",\"access-control-allow-origin\":\"*\",\"x-trace-id\":\"cb6bac1ceaf73365:71cda6ef30c41022:1ce6d682e96b77f5:1\",\"allow\":\"POST,DELETE\",\"vary\":\"Accept, Accept-Encoding\",\"content-type\":\"application/json; charset=utf-8\",\"content-length\":\"335\",\"etag\":\"W/\\\"14f-4opalGhfxX/2xl3T7JBx0h1FyXY\\\"\"}"}],"logs":[{"timestamp":1534172179631000,"fields":[{"key":"event","type":"string","value":"request_received"}]},{"timestamp":1534172180651000,"fields":[{"key":"event","type":"string","value":"request_finished"}]}],"processID":"p3","warnings":null}],"processes":{"p1":{"serviceName":"frontend","tags":[{"key":"hostname","type":"string","value":"685cd33f7b53"},{"key":"ip","type":"string","value":"192.168.112.10"},{"key":"jaeger.version","type":"string","value":"Java-0.27.0"}]},"p2":{"serviceName":"books","tags":[{"key":"client-uuid","type":"string","value":"9e464d71-6365-4802-be1f-58465732f682"},{"key":"ip","type":"float64","value":-1062703102},{"key":"jaeger.hostname","type":"string","value":"47bae12ebd8d"},{"key":"jaeger.version","type":"string","value":"Node-3.11.0"}]},"p3":{"serviceName":"users","tags":[{"key":"client-uuid","type":"string","value":"f652a29a-d1a4-41ba-9c08-cfef1ca91212"},{"key":"ip","type":"float64","value":-1062703098},{"key":"jaeger.hostname","type":"string","value":"df140c843700"},{"key":"jaeger.version","type":"string","value":"Node-3.11.0"}]}},"warnings":null},{"traceID":"69cc8203e5d49e10","spans":[{"traceID":"69cc8203e5d49e10","spanID":"6edeb5100ded99fd","flags":1,"operationName":"books","references":[{"refType":"CHILD_OF","traceID":"69cc8203e5d49e10","spanID":"d1746853947dd3bf"}],"startTime":1534172177466000,"duration":96000,"tags":[{"key":"span.kind","type":"string","value":"request"},{"key":"service.method","type":"string","value":"create"},{"key":"data","type":"string","value":"{\"isbn\":\"25403317906\",\"title\":\"title1\",\"author\":\"author1\",\"createdAt\":\"2018-08-13T14:56:17.467Z\",\"updatedAt\":\"2018-08-13T14:56:17.467Z\"}"},{"key":"http.status_code","type":"float64","value":201},{"key":"http.method","type":"string","value":"POST"},{"key":"peer.hostname","type":"string","value":"lbBooks"},{"key":"peer.address","type":"string","value":"192.168.112.9"},{"key":"request.headers","type":"string","value":"{\"accept\":\"text/plain, text/plain, application/json, application/json, application/*+json, application/*+json, */*, */*\",\"content-type\":\"application/json\",\"uber-trace-id\":\"69cc8203e5d49e10%3Ad1746853947dd3bf%3A69cc8203e5d49e10%3A1\",\"content-length\":\"63\",\"host\":\"lbBooks:80\",\"user-agent\":\"Apache-HttpClient/4.5.5 (Java/1.8.0_111)\",\"accept-encoding\":\"gzip,deflate\",\"x-forwarded-proto\":\"http\",\"x-forwarded-for\":\"192.168.112.9\"}"},{"key":"response.headers","type":"string","value":"{\"x-dns-prefetch-control\":\"off\",\"x-frame-options\":\"SAMEORIGIN\",\"strict-transport-security\":\"max-age=15552000; includeSubDomains\",\"x-download-options\":\"noopen\",\"x-content-type-options\":\"nosniff\",\"x-xss-protection\":\"1; mode=block\",\"access-control-allow-origin\":\"*\",\"x-trace-id\":\"69cc8203e5d49e10:6edeb5100ded99fd:d1746853947dd3bf:1\",\"allow\":\"GET,POST,PUT,PATCH,DELETE\",\"vary\":\"Accept, Accept-Encoding\",\"content-type\":\"application/json; charset=utf-8\",\"content-length\":\"161\",\"etag\":\"W/\\\"a1-Y45Lu97mkvmTuD+sjn8u6Jv6Ll8\\\"\"}"}],"logs":[{"timestamp":1534172177466000,"fields":[{"key":"event","type":"string","value":"request_received"}]},{"timestamp":1534172177562000,"fields":[{"key":"event","type":"string","value":"request_finished"}]}],"processID":"p1","warnings":null},{"traceID":"69cc8203e5d49e10","spanID":"27d484f810d1e449","flags":1,"operationName":"POST","references":[{"refType":"CHILD_OF","traceID":"69cc8203e5d49e10","spanID":"69cc8203e5d49e10"}],"startTime":1534172176366000,"duration":1050063,"tags":[{"key":"http.status_code","type":"int64","value":201},{"key":"component","type":"string","value":"java-spring-rest-template"},{"key":"span.kind","type":"string","value":"client"},{"key":"http.url","type":"string","value":"http://lbUsers:80/authentication"},{"key":"peer.port","type":"int64","value":80},{"key":"http.method","type":"string","value":"POST"}],"logs":[],"processID":"p2","warnings":null},{"traceID":"69cc8203e5d49e10","spanID":"d1746853947dd3bf","flags":1,"operationName":"POST","references":[{"refType":"CHILD_OF","traceID":"69cc8203e5d49e10","spanID":"69cc8203e5d49e10"}],"startTime":1534172177417000,"duration":146040,"tags":[{"key":"http.status_code","type":"int64","value":201},{"key":"component","type":"string","value":"java-spring-rest-template"},{"key":"span.kind","type":"string","value":"client"},{"key":"http.url","type":"string","value":"http://lbBooks:80/books"},{"key":"peer.port","type":"int64","value":80},{"key":"http.method","type":"string","value":"POST"}],"logs":[],"processID":"p2","warnings":null},{"traceID":"69cc8203e5d49e10","spanID":"69cc8203e5d49e10","flags":1,"operationName":"createBook","references":[],"startTime":1534172176361000,"duration":1205757,"tags":[{"key":"http.status_code","type":"int64","value":201},{"key":"component","type":"string","value":"java-web-servlet"},{"key":"span.kind","type":"string","value":"server"},{"key":"sampler.type","type":"string","value":"const"},{"key":"sampler.param","type":"bool","value":true},{"key":"http.url","type":"string","value":"http://localhost/createBook"},{"key":"pattern.circuitBreaker","type":"bool","value":true},{"key":"pattern.circuitBreaker.fallback","type":"bool","value":false},{"key":"http.method","type":"string","value":"GET"}],"logs":[{"timestamp":1534172176362000,"fields":[{"key":"event","type":"string","value":"preHandle"},{"key":"handler","type":"string","value":"public org.springframework.http.ResponseEntity\u003cjava.lang.String\u003e com.daimler.innolibrary_frontend.controller.BookController.createBook()"},{"key":"handler.class_simple_name","type":"string","value":"BookController"},{"key":"handler.method_name","type":"string","value":"createBook"}]},{"timestamp":1534172177567000,"fields":[{"key":"event","type":"string","value":"afterCompletion"},{"key":"handler","type":"string","value":"public org.springframework.http.ResponseEntity\u003cjava.lang.String\u003e com.daimler.innolibrary_frontend.controller.BookController.createBook()"}]}],"processID":"p2","warnings":null},{"traceID":"69cc8203e5d49e10","spanID":"efeeeb11087b12dd","flags":1,"operationName":"authentication","references":[{"refType":"CHILD_OF","traceID":"69cc8203e5d49e10","spanID":"27d484f810d1e449"}],"startTime":1534172176369000,"duration":1047000,"tags":[{"key":"span.kind","type":"string","value":"request"},{"key":"service.method","type":"string","value":"create"},{"key":"data","type":"string","value":"{\"email\":\"admin@admin.de\",\"password\":\"testpassword\",\"strategy\":\"local\"}"},{"key":"service.method","type":"string","value":"find"},{"key":"query","type":"string","value":"{\"email\":\"admin@admin.de\",\"$limit\":1}"},{"key":"http.status_code","type":"float64","value":201},{"key":"http.method","type":"string","value":"POST"},{"key":"peer.hostname","type":"string","value":"lbUsers"},{"key":"peer.address","type":"string","value":"192.168.112.9"},{"key":"request.headers","type":"string","value":"{\"accept\":\"text/plain, text/plain, application/json, application/json, application/*+json, application/*+json, */*, */*\",\"content-type\":\"application/json\",\"uber-trace-id\":\"69cc8203e5d49e10%3A27d484f810d1e449%3A69cc8203e5d49e10%3A1\",\"content-length\":\"80\",\"host\":\"lbUsers:80\",\"user-agent\":\"Apache-HttpClient/4.5.5 (Java/1.8.0_111)\",\"accept-encoding\":\"gzip,deflate\",\"x-forwarded-proto\":\"http\",\"x-forwarded-for\":\"192.168.112.9\"}"},{"key":"response.headers","type":"string","value":"{\"x-dns-prefetch-control\":\"off\",\"x-frame-options\":\"SAMEORIGIN\",\"strict-transport-security\":\"max-age=15552000; includeSubDomains\",\"x-download-options\":\"noopen\",\"x-content-type-options\":\"nosniff\",\"x-xss-protection\":\"1; mode=block\",\"access-control-allow-origin\":\"*\",\"x-trace-id\":\"69cc8203e5d49e10:efeeeb11087b12dd:27d484f810d1e449:1\",\"allow\":\"POST,DELETE\",\"vary\":\"Accept, Accept-Encoding\",\"content-type\":\"application/json; charset=utf-8\",\"content-length\":\"335\",\"etag\":\"W/\\\"14f-e4GKyRfNbPRWUpdl2s41d2IisnU\\\"\"}"}],"logs":[{"timestamp":1534172176370000,"fields":[{"key":"event","type":"string","value":"request_received"}]},{"timestamp":1534172177415000,"fields":[{"key":"event","type":"string","value":"request_finished"}]}],"processID":"p3","warnings":null}],"processes":{"p1":{"serviceName":"books","tags":[{"key":"client-uuid","type":"string","value":"9e464d71-6365-4802-be1f-58465732f682"},{"key":"ip","type":"float64","value":-1062703102},{"key":"jaeger.hostname","type":"string","value":"47bae12ebd8d"},{"key":"jaeger.version","type":"string","value":"Node-3.11.0"}]},"p2":{"serviceName":"frontend","tags":[{"key":"hostname","type":"string","value":"aae2095b2777"},{"key":"ip","type":"string","value":"192.168.112.9"},{"key":"jaeger.version","type":"string","value":"Java-0.27.0"}]},"p3":{"serviceName":"users","tags":[{"key":"client-uuid","type":"string","value":"05377051-6184-4b76-9b5b-2df32530b005"},{"key":"ip","type":"float64","value":-1062703099},{"key":"jaeger.hostname","type":"string","value":"a0afa8809983"},{"key":"jaeger.version","type":"string","value":"Node-3.11.0"}]}},"warnings":null},{"traceID":"e778fb51eb015682","spans":[{"traceID":"e778fb51eb015682","spanID":"db6569fa25170067","flags":1,"operationName":"POST","references":[{"refType":"CHILD_OF","traceID":"e778fb51eb015682","spanID":"e778fb51eb015682"}],"startTime":1534171905820000,"duration":1317017,"tags":[{"key":"http.status_code","type":"int64","value":201},{"key":"component","type":"string","value":"java-spring-rest-template"},{"key":"span.kind","type":"string","value":"client"},{"key":"http.url","type":"string","value":"http://lbUsers:80/authentication"},{"key":"peer.port","type":"int64","value":80},{"key":"http.method","type":"string","value":"POST"}],"logs":[],"processID":"p1","warnings":null},{"traceID":"e778fb51eb015682","spanID":"9b7ccaea907fb035","flags":1,"operationName":"GET","references":[{"refType":"CHILD_OF","traceID":"e778fb51eb015682","spanID":"e778fb51eb015682"}],"startTime":1534171907141000,"duration":71222,"tags":[{"key":"http.status_code","type":"int64","value":200},{"key":"component","type":"string","value":"java-spring-rest-template"},{"key":"span.kind","type":"string","value":"client"},{"key":"http.url","type":"string","value":"http://lbBooks:80/books"},{"key":"peer.port","type":"int64","value":80},{"key":"http.method","type":"string","value":"GET"}],"logs":[],"processID":"p1","warnings":null},{"traceID":"e778fb51eb015682","spanID":"e778fb51eb015682","flags":1,"operationName":"getCatalog","references":[],"startTime":1534171901788000,"duration":5517753,"tags":[{"key":"http.status_code","type":"int64","value":200},{"key":"component","type":"string","value":"java-web-servlet"},{"key":"span.kind","type":"string","value":"server"},{"key":"sampler.type","type":"string","value":"const"},{"key":"sampler.param","type":"bool","value":true},{"key":"http.url","type":"string","value":"http://localhost/catalog"},{"key":"pattern.circuitBreaker","type":"bool","value":true},{"key":"pattern.circuitBreaker.fallback","type":"bool","value":false},{"key":"http.method","type":"string","value":"GET"}],"logs":[{"timestamp":1534171901882000,"fields":[{"key":"event","type":"string","value":"preHandle"},{"key":"handler","type":"string","value":"public org.springframework.http.ResponseEntity\u003cjava.lang.String\u003e com.daimler.innolibrary_frontend.controller.BookController.getCatalog()"},{"key":"handler.class_simple_name","type":"string","value":"BookController"},{"key":"handler.method_name","type":"string","value":"getCatalog"}]},{"timestamp":1534171907305000,"fields":[{"key":"event","type":"string","value":"afterCompletion"},{"key":"handler","type":"string","value":"public org.springframework.http.ResponseEntity\u003cjava.lang.String\u003e com.daimler.innolibrary_frontend.controller.BookController.getCatalog()"}]}],"processID":"p1","warnings":null},{"traceID":"e778fb51eb015682","spanID":"2b3a13fbe51fab61","flags":1,"operationName":"books","references":[{"refType":"CHILD_OF","traceID":"e778fb51eb015682","spanID":"9b7ccaea907fb035"}],"startTime":1534171907166611,"duration":20000,"tags":[{"key":"span.kind","type":"string","value":"request"},{"key":"service.method","type":"string","value":"find"},{"key":"http.status_code","type":"float64","value":200},{"key":"http.method","type":"string","value":"GET"},{"key":"peer.hostname","type":"string","value":"lbBooks"},{"key":"peer.address","type":"string","value":"192.168.112.9"},{"key":"request.headers","type":"string","value":"{\"accept\":\"text/plain, text/plain, application/json, application/json, application/*+json, application/*+json, */*, */*\",\"uber-trace-id\":\"e778fb51eb015682%3A9b7ccaea907fb035%3Ae778fb51eb015682%3A1\",\"host\":\"lbBooks:80\",\"user-agent\":\"Apache-HttpClient/4.5.5 (Java/1.8.0_111)\",\"accept-encoding\":\"gzip,deflate\",\"x-forwarded-proto\":\"http\",\"x-forwarded-for\":\"192.168.112.9\"}"},{"key":"response.headers","type":"string","value":"{\"x-dns-prefetch-control\":\"off\",\"x-frame-options\":\"SAMEORIGIN\",\"strict-transport-security\":\"max-age=15552000; includeSubDomains\",\"x-download-options\":\"noopen\",\"x-content-type-options\":\"nosniff\",\"x-xss-protection\":\"1; mode=block\",\"access-control-allow-origin\":\"*\",\"x-trace-id\":\"e778fb51eb015682:2b3a13fbe51fab61:9b7ccaea907fb035:1\",\"allow\":\"GET,POST,PUT,PATCH,DELETE\",\"vary\":\"Accept, Accept-Encoding\",\"content-type\":\"application/json; charset=utf-8\",\"content-length\":\"310\",\"etag\":\"W/\\\"136-70DPyXYeb7xX8buh8QHiNSjqetA\\\"\"}"}],"logs":[{"timestamp":1534171907168611,"fields":[{"key":"event","type":"string","value":"request_received"}]},{"timestamp":1534171907185611,"fields":[{"key":"event","type":"string","value":"request_finished"}]}],"processID":"p2","warnings":null},{"traceID":"e778fb51eb015682","spanID":"634b58538e89a199","flags":1,"operationName":"authentication","references":[{"refType":"CHILD_OF","traceID":"e778fb51eb015682","spanID":"db6569fa25170067"}],"startTime":1534171906124000,"duration":1009000,"tags":[{"key":"span.kind","type":"string","value":"request"},{"key":"service.method","type":"string","value":"create"},{"key":"data","type":"string","value":"{\"email\":\"admin@admin.de\",\"password\":\"testpassword\",\"strategy\":\"local\"}"},{"key":"service.method","type":"string","value":"find"},{"key":"query","type":"string","value":"{\"email\":\"admin@admin.de\",\"$limit\":1}"},{"key":"http.status_code","type":"float64","value":201},{"key":"http.method","type":"string","value":"POST"},{"key":"peer.hostname","type":"string","value":"lbUsers"},{"key":"peer.address","type":"string","value":"192.168.112.9"},{"key":"request.headers","type":"string","value":"{\"accept\":\"text/plain, text/plain, application/json, application/json, application/*+json, application/*+json, */*, */*\",\"content-type\":\"application/json\",\"uber-trace-id\":\"e778fb51eb015682%3Adb6569fa25170067%3Ae778fb51eb015682%3A1\",\"content-length\":\"80\",\"host\":\"lbUsers:80\",\"user-agent\":\"Apache-HttpClient/4.5.5 (Java/1.8.0_111)\",\"accept-encoding\":\"gzip,deflate\",\"x-forwarded-proto\":\"http\",\"x-forwarded-for\":\"192.168.112.9\"}"},{"key":"response.headers","type":"string","value":"{\"x-dns-prefetch-control\":\"off\",\"x-frame-options\":\"SAMEORIGIN\",\"strict-transport-security\":\"max-age=15552000; includeSubDomains\",\"x-download-options\":\"noopen\",\"x-content-type-options\":\"nosniff\",\"x-xss-protection\":\"1; mode=block\",\"access-control-allow-origin\":\"*\",\"x-trace-id\":\"e778fb51eb015682:634b58538e89a199:db6569fa25170067:1\",\"allow\":\"POST,DELETE\",\"vary\":\"Accept, Accept-Encoding\",\"content-type\":\"application/json; charset=utf-8\",\"content-length\":\"335\",\"etag\":\"W/\\\"14f-MO1TzqHGjeTW00XEV2uuiV9zutQ\\\"\"}"}],"logs":[{"timestamp":1534171906125000,"fields":[{"key":"event","type":"string","value":"request_received"}]},{"timestamp":1534171907132000,"fields":[{"key":"event","type":"string","value":"request_finished"}]}],"processID":"p3","warnings":null}],"processes":{"p1":{"serviceName":"frontend","tags":[{"key":"hostname","type":"string","value":"aae2095b2777"},{"key":"ip","type":"string","value":"192.168.112.9"},{"key":"jaeger.version","type":"string","value":"Java-0.27.0"}]},"p2":{"serviceName":"books","tags":[{"key":"client-uuid","type":"string","value":"9e464d71-6365-4802-be1f-58465732f682"},{"key":"ip","type":"float64","value":-1062703102},{"key":"jaeger.hostname","type":"string","value":"47bae12ebd8d"},{"key":"jaeger.version","type":"string","value":"Node-3.11.0"}]},"p3":{"serviceName":"users","tags":[{"key":"client-uuid","type":"string","value":"05377051-6184-4b76-9b5b-2df32530b005"},{"key":"ip","type":"float64","value":-1062703099},{"key":"jaeger.hostname","type":"string","value":"a0afa8809983"},{"key":"jaeger.version","type":"string","value":"Node-3.11.0"}]}},"warnings":null},{"traceID":"9dafded51b307078","spans":[{"traceID":"9dafded51b307078","spanID":"f824e30b821c7790","flags":1,"operationName":"POST","references":[{"refType":"CHILD_OF","traceID":"9dafded51b307078","spanID":"9dafded51b307078"}],"startTime":1534172172724000,"duration":1005365,"tags":[{"key":"http.status_code","type":"int64","value":201},{"key":"component","type":"string","value":"java-spring-rest-template"},{"key":"span.kind","type":"string","value":"client"},{"key":"http.url","type":"string","value":"http://lbUsers:80/authentication"},{"key":"peer.port","type":"int64","value":80},{"key":"http.method","type":"string","value":"POST"}],"logs":[],"processID":"p1","warnings":null},{"traceID":"9dafded51b307078","spanID":"dd13e017e27c84c8","flags":1,"operationName":"POST","references":[{"refType":"CHILD_OF","traceID":"9dafded51b307078","spanID":"9dafded51b307078"}],"startTime":1534172173731000,"duration":6230,"tags":[{"key":"http.status_code","type":"int64","value":201},{"key":"component","type":"string","value":"java-spring-rest-template"},{"key":"span.kind","type":"string","value":"client"},{"key":"http.url","type":"string","value":"http://lbBooks:80/books"},{"key":"peer.port","type":"int64","value":80},{"key":"http.method","type":"string","value":"POST"}],"logs":[],"processID":"p1","warnings":null},{"traceID":"9dafded51b307078","spanID":"9dafded51b307078","flags":1,"operationName":"createBook","references":[],"startTime":1534172172711000,"duration":1030983,"tags":[{"key":"http.status_code","type":"int64","value":201},{"key":"component","type":"string","value":"java-web-servlet"},{"key":"span.kind","type":"string","value":"server"},{"key":"sampler.type","type":"string","value":"const"},{"key":"sampler.param","type":"bool","value":true},{"key":"http.url","type":"string","value":"http://localhost/createBook"},{"key":"pattern.circuitBreaker","type":"bool","value":true},{"key":"pattern.circuitBreaker.fallback","type":"bool","value":false},{"key":"http.method","type":"string","value":"GET"}],"logs":[{"timestamp":1534172172712000,"fields":[{"key":"event","type":"string","value":"preHandle"},{"key":"handler","type":"string","value":"public org.springframework.http.ResponseEntity\u003cjava.lang.String\u003e com.daimler.innolibrary_frontend.controller.BookController.createBook()"},{"key":"handler.class_simple_name","type":"string","value":"BookController"},{"key":"handler.method_name","type":"string","value":"createBook"}]},{"timestamp":1534172173742000,"fields":[{"key":"event","type":"string","value":"afterCompletion"},{"key":"handler","type":"string","value":"public org.springframework.http.ResponseEntity\u003cjava.lang.String\u003e com.daimler.innolibrary_frontend.controller.BookController.createBook()"}]}],"processID":"p1","warnings":null},{"traceID":"9dafded51b307078","spanID":"d53e2338ce1b9101","flags":1,"operationName":"authentication","references":[{"refType":"CHILD_OF","traceID":"9dafded51b307078","spanID":"f824e30b821c7790"}],"startTime":1534172172726000,"duration":1003000,"tags":[{"key":"span.kind","type":"string","value":"request"},{"key":"service.method","type":"string","value":"create"},{"key":"data","type":"string","value":"{\"email\":\"admin@admin.de\",\"password\":\"testpassword\",\"strategy\":\"local\"}"},{"key":"service.method","type":"string","value":"find"},{"key":"query","type":"string","value":"{\"email\":\"admin@admin.de\",\"$limit\":1}"},{"key":"http.status_code","type":"float64","value":201},{"key":"http.method","type":"string","value":"POST"},{"key":"peer.hostname","type":"string","value":"lbUsers"},{"key":"peer.address","type":"string","value":"192.168.112.9"},{"key":"request.headers","type":"string","value":"{\"accept\":\"text/plain, text/plain, application/json, application/json, application/*+json, application/*+json, */*, */*\",\"content-type\":\"application/json\",\"uber-trace-id\":\"9dafded51b307078%3Af824e30b821c7790%3A9dafded51b307078%3A1\",\"content-length\":\"80\",\"host\":\"lbUsers:80\",\"user-agent\":\"Apache-HttpClient/4.5.5 (Java/1.8.0_111)\",\"accept-encoding\":\"gzip,deflate\",\"x-forwarded-proto\":\"http\",\"x-forwarded-for\":\"192.168.112.9\"}"},{"key":"response.headers","type":"string","value":"{\"x-dns-prefetch-control\":\"off\",\"x-frame-options\":\"SAMEORIGIN\",\"strict-transport-security\":\"max-age=15552000; includeSubDomains\",\"x-download-options\":\"noopen\",\"x-content-type-options\":\"nosniff\",\"x-xss-protection\":\"1; mode=block\",\"access-control-allow-origin\":\"*\",\"x-trace-id\":\"9dafded51b307078:d53e2338ce1b9101:f824e30b821c7790:1\",\"allow\":\"POST,DELETE\",\"vary\":\"Accept, Accept-Encoding\",\"content-type\":\"application/json; charset=utf-8\",\"content-length\":\"335\",\"etag\":\"W/\\\"14f-uwUSERcG/dChn8+kL3PpIj2Tcco\\\"\"}"}],"logs":[{"timestamp":1534172172726000,"fields":[{"key":"event","type":"string","value":"request_received"}]},{"timestamp":1534172173729000,"fields":[{"key":"event","type":"string","value":"request_finished"}]}],"processID":"p2","warnings":null},{"traceID":"9dafded51b307078","spanID":"85bc19ebb201056a","flags":1,"operationName":"books","references":[{"refType":"CHILD_OF","traceID":"9dafded51b307078","spanID":"dd13e017e27c84c8"}],"startTime":1534172173735000,"duration":2000,"tags":[{"key":"span.kind","type":"string","value":"request"},{"key":"service.method","type":"string","value":"create"},{"key":"data","type":"string","value":"{\"isbn\":\"20764223382\",\"title\":\"title0\",\"author\":\"author0\",\"createdAt\":\"2018-08-13T14:56:13.735Z\",\"updatedAt\":\"2018-08-13T14:56:13.735Z\"}"},{"key":"http.status_code","type":"float64","value":201},{"key":"http.method","type":"string","value":"POST"},{"key":"peer.hostname","type":"string","value":"lbBooks"},{"key":"peer.address","type":"string","value":"192.168.112.9"},{"key":"request.headers","type":"string","value":"{\"accept\":\"text/plain, text/plain, application/json, application/json, application/*+json, application/*+json, */*, */*\",\"content-type\":\"application/json\",\"uber-trace-id\":\"9dafded51b307078%3Add13e017e27c84c8%3A9dafded51b307078%3A1\",\"content-length\":\"63\",\"host\":\"lbBooks:80\",\"user-agent\":\"Apache-HttpClient/4.5.5 (Java/1.8.0_111)\",\"accept-encoding\":\"gzip,deflate\",\"x-forwarded-proto\":\"http\",\"x-forwarded-for\":\"192.168.112.9\"}"},{"key":"response.headers","type":"string","value":"{\"x-dns-prefetch-control\":\"off\",\"x-frame-options\":\"SAMEORIGIN\",\"strict-transport-security\":\"max-age=15552000; includeSubDomains\",\"x-download-options\":\"noopen\",\"x-content-type-options\":\"nosniff\",\"x-xss-protection\":\"1; mode=block\",\"access-control-allow-origin\":\"*\",\"x-trace-id\":\"9dafded51b307078:85bc19ebb201056a:dd13e017e27c84c8:1\",\"allow\":\"GET,POST,PUT,PATCH,DELETE\",\"vary\":\"Accept, Accept-Encoding\",\"content-type\":\"application/json; charset=utf-8\",\"content-length\":\"161\",\"etag\":\"W/\\\"a1-k+kZK/KuuNg7cHzE0b/iGKcgsP4\\\"\"}"}],"logs":[{"timestamp":1534172173735000,"fields":[{"key":"event","type":"string","value":"request_received"}]},{"timestamp":1534172173737000,"fields":[{"key":"event","type":"string","value":"request_finished"}]}],"processID":"p3","warnings":null}],"processes":{"p1":{"serviceName":"frontend","tags":[{"key":"hostname","type":"string","value":"aae2095b2777"},{"key":"ip","type":"string","value":"192.168.112.9"},{"key":"jaeger.version","type":"string","value":"Java-0.27.0"}]},"p2":{"serviceName":"users","tags":[{"key":"client-uuid","type":"string","value":"f652a29a-d1a4-41ba-9c08-cfef1ca91212"},{"key":"ip","type":"float64","value":-1062703098},{"key":"jaeger.hostname","type":"string","value":"df140c843700"},{"key":"jaeger.version","type":"string","value":"Node-3.11.0"}]},"p3":{"serviceName":"books","tags":[{"key":"client-uuid","type":"string","value":"9e464d71-6365-4802-be1f-58465732f682"},{"key":"ip","type":"float64","value":-1062703102},{"key":"jaeger.hostname","type":"string","value":"47bae12ebd8d"},{"key":"jaeger.version","type":"string","value":"Node-3.11.0"}]}},"warnings":null},{"traceID":"52d5e21ec20a18bc","spans":[{"traceID":"52d5e21ec20a18bc","spanID":"d7bdfbe69b7c6a89","flags":1,"operationName":"books","references":[{"refType":"CHILD_OF","traceID":"52d5e21ec20a18bc","spanID":"7fc5439144148274"}],"startTime":1534172129140000,"duration":1000,"tags":[{"key":"span.kind","type":"string","value":"request"},{"key":"service.method","type":"string","value":"find"},{"key":"http.status_code","type":"float64","value":200},{"key":"http.method","type":"string","value":"GET"},{"key":"peer.hostname","type":"string","value":"lbBooks"},{"key":"peer.address","type":"string","value":"192.168.112.9"},{"key":"request.headers","type":"string","value":"{\"accept\":\"text/plain, text/plain, application/json, application/json, application/*+json, application/*+json, */*, */*\",\"uber-trace-id\":\"52d5e21ec20a18bc%3A7fc5439144148274%3A52d5e21ec20a18bc%3A1\",\"host\":\"lbBooks:80\",\"user-agent\":\"Apache-HttpClient/4.5.5 (Java/1.8.0_111)\",\"accept-encoding\":\"gzip,deflate\",\"x-forwarded-proto\":\"http\",\"x-forwarded-for\":\"192.168.112.9\"}"},{"key":"response.headers","type":"string","value":"{\"x-dns-prefetch-control\":\"off\",\"x-frame-options\":\"SAMEORIGIN\",\"strict-transport-security\":\"max-age=15552000; includeSubDomains\",\"x-download-options\":\"noopen\",\"x-content-type-options\":\"nosniff\",\"x-xss-protection\":\"1; mode=block\",\"access-control-allow-origin\":\"*\",\"x-trace-id\":\"52d5e21ec20a18bc:d7bdfbe69b7c6a89:7fc5439144148274:1\",\"allow\":\"GET,POST,PUT,PATCH,DELETE\",\"vary\":\"Accept, Accept-Encoding\",\"content-type\":\"application/json; charset=utf-8\",\"content-length\":\"310\",\"etag\":\"W/\\\"136-70DPyXYeb7xX8buh8QHiNSjqetA\\\"\"}"}],"logs":[{"timestamp":1534172129140000,"fields":[{"key":"event","type":"string","value":"request_received"}]},{"timestamp":1534172129141000,"fields":[{"key":"event","type":"string","value":"request_finished"}]}],"processID":"p1","warnings":null},{"traceID":"52d5e21ec20a18bc","spanID":"5ab1f5c9ea4d7d09","flags":1,"operationName":"POST","references":[{"refType":"CHILD_OF","traceID":"52d5e21ec20a18bc","spanID":"52d5e21ec20a18bc"}],"startTime":1534172128099000,"duration":1036748,"tags":[{"key":"http.status_code","type":"int64","value":201},{"key":"component","type":"string","value":"java-spring-rest-template"},{"key":"span.kind","type":"string","value":"client"},{"key":"http.url","type":"string","value":"http://lbUsers:80/authentication"},{"key":"peer.port","type":"int64","value":80},{"key":"http.method","type":"string","value":"POST"}],"logs":[],"processID":"p2","warnings":null},{"traceID":"52d5e21ec20a18bc","spanID":"52d5e21ec20a18bc","flags":1,"operationName":"getCatalog","references":[],"startTime":1534172128030000,"duration":1126890,"tags":[{"key":"http.status_code","type":"int64","value":304},{"key":"component","type":"string","value":"java-web-servlet"},{"key":"span.kind","type":"string","value":"server"},{"key":"sampler.type","type":"string","value":"const"},{"key":"sampler.param","type":"bool","value":true},{"key":"http.url","type":"string","value":"http://localhost/catalog"},{"key":"pattern.circuitBreaker","type":"bool","value":true},{"key":"pattern.circuitBreaker.fallback","type":"bool","value":false},{"key":"http.method","type":"string","value":"GET"}],"logs":[{"timestamp":1534172128031000,"fields":[{"key":"event","type":"string","value":"preHandle"},{"key":"handler","type":"string","value":"public org.springframework.http.ResponseEntity\u003cjava.lang.String\u003e com.daimler.innolibrary_frontend.controller.BookController.getCatalog()"},{"key":"handler.class_simple_name","type":"string","value":"BookController"},{"key":"handler.method_name","type":"string","value":"getCatalog"}]},{"timestamp":1534172129157000,"fields":[{"key":"event","type":"string","value":"afterCompletion"},{"key":"handler","type":"string","value":"public org.springframework.http.ResponseEntity\u003cjava.lang.String\u003e com.daimler.innolibrary_frontend.controller.BookController.getCatalog()"}]}],"processID":"p2","warnings":null},{"traceID":"52d5e21ec20a18bc","spanID":"7fc5439144148274","flags":1,"operationName":"GET","references":[{"refType":"CHILD_OF","traceID":"52d5e21ec20a18bc","spanID":"52d5e21ec20a18bc"}],"startTime":1534172129137000,"duration":5043,"tags":[{"key":"http.status_code","type":"int64","value":200},{"key":"component","type":"string","value":"java-spring-rest-template"},{"key":"span.kind","type":"string","value":"client"},{"key":"http.url","type":"string","value":"http://lbBooks:80/books"},{"key":"peer.port","type":"int64","value":80},{"key":"http.method","type":"string","value":"GET"}],"logs":[],"processID":"p2","warnings":null},{"traceID":"52d5e21ec20a18bc","spanID":"2a0eec868494b038","flags":1,"operationName":"authentication","references":[{"refType":"CHILD_OF","traceID":"52d5e21ec20a18bc","spanID":"5ab1f5c9ea4d7d09"}],"startTime":1534172128104000,"duration":1031000,"tags":[{"key":"span.kind","type":"string","value":"request"},{"key":"service.method","type":"string","value":"create"},{"key":"data","type":"string","value":"{\"email\":\"admin@admin.de\",\"password\":\"testpassword\",\"strategy\":\"local\"}"},{"key":"service.method","type":"string","value":"find"},{"key":"query","type":"string","value":"{\"email\":\"admin@admin.de\",\"$limit\":1}"},{"key":"http.status_code","type":"float64","value":201},{"key":"http.method","type":"string","value":"POST"},{"key":"peer.hostname","type":"string","value":"lbUsers"},{"key":"peer.address","type":"string","value":"192.168.112.9"},{"key":"request.headers","type":"string","value":"{\"accept\":\"text/plain, text/plain, application/json, application/json, application/*+json, application/*+json, */*, */*\",\"content-type\":\"application/json\",\"uber-trace-id\":\"52d5e21ec20a18bc%3A5ab1f5c9ea4d7d09%3A52d5e21ec20a18bc%3A1\",\"content-length\":\"80\",\"host\":\"lbUsers:80\",\"user-agent\":\"Apache-HttpClient/4.5.5 (Java/1.8.0_111)\",\"accept-encoding\":\"gzip,deflate\",\"x-forwarded-proto\":\"http\",\"x-forwarded-for\":\"192.168.112.9\"}"},{"key":"response.headers","type":"string","value":"{\"x-dns-prefetch-control\":\"off\",\"x-frame-options\":\"SAMEORIGIN\",\"strict-transport-security\":\"max-age=15552000; includeSubDomains\",\"x-download-options\":\"noopen\",\"x-content-type-options\":\"nosniff\",\"x-xss-protection\":\"1; mode=block\",\"access-control-allow-origin\":\"*\",\"x-trace-id\":\"52d5e21ec20a18bc:2a0eec868494b038:5ab1f5c9ea4d7d09:1\",\"allow\":\"POST,DELETE\",\"vary\":\"Accept, Accept-Encoding\",\"content-type\":\"application/json; charset=utf-8\",\"content-length\":\"335\",\"etag\":\"W/\\\"14f-uDnJJzNdhbCM2WYXZjsS1Jb+23M\\\"\"}"}],"logs":[{"timestamp":1534172128105000,"fields":[{"key":"event","type":"string","value":"request_received"}]},{"timestamp":1534172129135000,"fields":[{"key":"event","type":"string","value":"request_finished"}]}],"processID":"p3","warnings":null}],"processes":{"p1":{"serviceName":"books","tags":[{"key":"client-uuid","type":"string","value":"9e464d71-6365-4802-be1f-58465732f682"},{"key":"ip","type":"float64","value":-1062703102},{"key":"jaeger.hostname","type":"string","value":"47bae12ebd8d"},{"key":"jaeger.version","type":"string","value":"Node-3.11.0"}]},"p2":{"serviceName":"frontend","tags":[{"key":"hostname","type":"string","value":"aae2095b2777"},{"key":"ip","type":"string","value":"192.168.112.9"},{"key":"jaeger.version","type":"string","value":"Java-0.27.0"}]},"p3":{"serviceName":"users","tags":[{"key":"client-uuid","type":"string","value":"f652a29a-d1a4-41ba-9c08-cfef1ca91212"},{"key":"ip","type":"float64","value":-1062703098},{"key":"jaeger.hostname","type":"string","value":"df140c843700"},{"key":"jaeger.version","type":"string","value":"Node-3.11.0"}]}},"warnings":null}],"total":0,"limit":0,"offset":0,"errors":null}